readbktbls/__init__.py
readbktbls/connect_and_read.py
readbktbls/connect_and_read_api.py
readdatabrickstables-0.2.0.dist-info/METADATA
readdatabrickstables-0.2.0.dist-info/WHEEL
readdatabrickstables-0.2.0.dist-info/top_level.txt
wheel_old/readdatabrickstables-0.1.5.dist-info/WHEEL
wheel_old/readdatabrickstables-0.1.5.dist-info/dependency_links.txt
wheel_old/readdatabrickstables-0.1.5.dist-info/top_level.txt
wheel_old/readdatabrickstables-0.1.6.dist-info/METADATA
wheel_old/readdatabrickstables-0.1.6.dist-info/WHEEL
wheel_old/readdatabrickstables-0.1.6.dist-info/dependency_links.txt
wheel_old/readdatabrickstables-0.1.6.dist-info/top_level.txt
wheel_old/readdatabrickstables-0.1.7.dist-info/METADATA
wheel_old/readdatabrickstables-0.1.7.dist-info/WHEEL
wheel_old/readdatabrickstables-0.1.7.dist-info/dependency_links.txt
wheel_old/readdatabrickstables-0.1.7.dist-info/top_level.txt
wheel_old/readdatabrickstables-0.2.0.dist-info/METADATA
wheel_old/readdatabrickstables-0.2.0.dist-info/WHEEL
wheel_old/readdatabrickstables-0.2.0.dist-info/dependency_links.txt
wheel_old/readdatabrickstables-0.2.0.dist-info/top_level.txt
readdatabrickstables-0.2.0.dist-info/RECORD
